MANIFEST.in
README.md
setup.py
motifer/__init__.py
motifer/fast_api_factory.py
motifer/fast_api_filters.py
motifer/filters.py
motifer/flask_factory.py
motifer/formatters.py
motifer/logger_factory.py
motifer/su_alert.py
motifer.egg-info/PKG-INFO
motifer.egg-info/SOURCES.txt
motifer.egg-info/dependency_links.txt
motifer.egg-info/requires.txt
motifer.egg-info/top_level.txt