Metadata-Version: 2.1
Name: motifer
Version: 1.1.3
Summary: Generic logs pattern builder for Python and Flask, built on top of logging module.
Home-page: https://www.searchunify.com/
Author: Ankur Mahajan
Author-email: mahajanankur.nith@gmail.com
License: Apache License
Project-URL: Documentation, https://github.com/mahajanankur/motifer-py/blob/main/README.md
Project-URL: Source, https://github.com/mahajanankur/motifer-py
Platform: UNKNOWN
Classifier: Development Status :: 5 - Production/Stable
Classifier: Intended Audience :: Developers
Classifier: Natural Language :: English
Classifier: License :: OSI Approved :: Apache Software License
Classifier: Programming Language :: Python
Classifier: Programming Language :: Python :: 3
Classifier: Programming Language :: Python :: 3.7
Classifier: Programming Language :: Python :: 3.8
Classifier: Programming Language :: Python :: 3.9
Classifier: Programming Language :: Python :: 3.10
Classifier: Programming Language :: Python :: 3.11
Requires-Python: >= 3
